datalyzer/__init__.py
datalyzer/__main__.py
datalyzer/cli.py
datalyzer/config.py
datalyzer/core.py
datalyzer/plots.py
datalyzer/report.py
datalyzer/stats.py
datalyzer/utils.py
smart_datalyzer-0.1.1.dist-info/METADATA
smart_datalyzer-0.1.1.dist-info/WHEEL
smart_datalyzer-0.1.1.dist-info/entry_points.txt
smart_datalyzer-0.1.1.dist-info/top_level.txt
smart_datalyzer-0.1.1.dist-info/RECORD
