Metadata-Version: 2.4
Name: smart-datalyzer
Version: 0.1.1
Summary: Data analysis and reporting toolkit
Home-page: https://github.com/mehmoodulhaq570/smart-datalyzer
Author: Mehmood Ul Haq
Author-email: Mehmood Ul Haq <mehmoodulhaq1040@gmail.com>
License: MIT
Project-URL: Homepage, https://github.com/mehmoodulhaq570/smart-datalyzer
Project-URL: BugTracker, https://github.com/mehmoodulhaq570/smart-datalyzer/issues
Classifier: Programming Language :: Python :: 3
Classifier: License :: OSI Approved :: MIT License
Classifier: Operating System :: OS Independent
Requires-Python: >=3.8
Requires-Dist: pandas
Requires-Dist: numpy
Requires-Dist: scipy
Requires-Dist: statsmodels
Requires-Dist: scikit-learn
Requires-Dist: matplotlib
Requires-Dist: seaborn
Requires-Dist: rich
Dynamic: author
Dynamic: home-page
Dynamic: requires-python
